s3sync/__init__.py
s3sync/controllers/__init__.py
s3sync/controllers/interface.py
s3sync/controllers/localtos3.py
s3sync/controllers/s3tolocal.py
s3sync/controllers/s3tos3.py
s3sync/schemas/__init__.py
s3sync/schemas/local.py
s3sync/schemas/s3.py
s3sync/services/__init__.py
s3sync/services/interface.py
s3sync/services/local.py
s3sync/services/s3.py
s3sync/utils/__init__.py
s3sync/utils/util.py
s3sync-0.1.1.dist-info/LICENSE
s3sync-0.1.1.dist-info/METADATA
s3sync-0.1.1.dist-info/WHEEL
s3sync-0.1.1.dist-info/entry_points.txt
s3sync-0.1.1.dist-info/RECORD
