Metadata-Version: 2.1
Name: s3sync
Version: 0.1.1
Summary: Sync s3 from one source to another place
License: MIT
Author: Ferdina Kusumah
Author-email: ferdina.kusumah@gmail.com
Requires-Python: >=3.10,<4.0
Classifier: License :: OSI Approved :: MIT License
Classifier: Programming Language :: Python :: 3
Classifier: Programming Language :: Python :: 3.10
Classifier: Programming Language :: Python :: 3.11
Requires-Dist: boto3 (>=1.34.14,<2.0.0)
Requires-Dist: pydantic (>=2.5.3,<3.0.0)
Requires-Dist: tqdm (>=4.66.1,<5.0.0)
